mdwarf_contin/.DS_Store
mdwarf_contin/__init__.py
mdwarf_contin/manipulate_spectra.py
mdwarf_contin/normalize.py
mdwarf_contin/response_data/__init__.py
mdwarf_contin/response_data/resp_PCA_results.npz
mdwarf_contin-1.0.0.dist-info/LICENSE.md
mdwarf_contin-1.0.0.dist-info/METADATA
mdwarf_contin-1.0.0.dist-info/WHEEL
mdwarf_contin-1.0.0.dist-info/RECORD
