Metadata-Version: 2.1
Name: mdwarf-contin
Version: 1.0.0
Summary: 
Author: imedan
Author-email: ilija.medan@vanderbilt.edu
Requires-Python: >=3.10,<4.0
Classifier: Programming Language :: Python :: 3
Classifier: Programming Language :: Python :: 3.10
Classifier: Programming Language :: Python :: 3.11
Classifier: Programming Language :: Python :: 3.12
Requires-Dist: alpha-shapes (>=1.1.0,<2.0.0)
Requires-Dist: astropy (>=6.0.0,<7.0.0)
Requires-Dist: localreg (>=0.5.0,<0.6.0)
Requires-Dist: numpy (>=1.26.4,<2.0.0)
Requires-Dist: shapely (>=2.0.3,<3.0.0)
